pinappleclient/__init__.py
pinappleclient/client.py
pinappleclient/manual.py
pinappleclient/test.py
pinappleclient-2.0.2.dist-info/licenses/LICENSE
pinappleclient-2.0.2.dist-info/METADATA
pinappleclient-2.0.2.dist-info/WHEEL
pinappleclient-2.0.2.dist-info/top_level.txt
pinappleclient-2.0.2.dist-info/RECORD
