Metadata-Version: 2.4
Name: PinappleClient
Version: 2.0.2
Summary: Client for interacting with Pinapple
Author-email: Erik Bremstedt <erik.bremstedt-pedersen@regionstockholm.se>
License: GPL-3.0
Project-URL: Homepage, https://github.com/ebremst3dt/pinappleclient
Project-URL: Issues, https://github.com/ebremst3dt/pinappleclient/issues
Classifier: Programming Language :: Python :: 3
Classifier: Programming Language :: Python :: 3.12
Classifier: License :: OSI Approved :: GNU General Public License v3 (GPLv3)
Classifier: Operating System :: OS Independent
Requires-Python: >=3.12
License-File: LICENSE
Requires-Dist: requests<3.0.0,>=2.25.0
Requires-Dist: pandas<3.0.0,>=1.3.0
Requires-Dist: roskarl<3.0.0,>=2.0.0
Dynamic: license-file
